{
	"name": "DevTrainingDS",
	"properties": {
		"linkedServiceName": {
			"referenceName": "AzureBlobStorageLS",
			"type": "LinkedServiceReference"
		},
		"annotations": [],
		"type": "DelimitedText",
		"typeProperties": {
			"location": {
				"type": "AzureBlobStorageLocation",
				"fileName": "DevTraining_Dirty.csv",
				"folderPath": "folderkiki_dirty",
				"container": "containerkiki"
			},
			"columnDelimiter": ",",
			"escapeChar": "\\",
			"firstRowAsHeader": true,
			"quoteChar": "\""
		},
		"schema": [
			{
				"name": "Education",
				"type": "String"
			},
			{
				"name": "EducationField",
				"type": "String"
			},
			{
				"name": "TrainingTimesLastYear",
				"type": "String"
			},
			{
				"name": "EmployeeName",
				"type": "String"
			},
			{
				"name": "EmployeeDTNumber",
				"type": "String"
			}
		]
	}
}